__init__.py
constants.py
dea.py
person_name.py
provider_individual.py
taxonomy_generator.py
faker_healthcare_system-0.1.24.data/data/assets/nucc_taxonomy_231.csv
faker_healthcare_system-0.1.24.dist-info/METADATA
faker_healthcare_system-0.1.24.dist-info/WHEEL
faker_healthcare_system-0.1.24.dist-info/top_level.txt
faker_healthcare_system-0.1.24.dist-info/RECORD
